{
    "wallpaper": "/home/gabe/pics/wals/portraits/phil.jpg",
    "alpha": "100",
    "special": {
        "background": "#faf9f8",
        "foreground": "#3e3e3e",
        "cursor": "#3e3e3e"
    },
    "colors": {
        "color0": "#faf9f8",
        "color1": "#a6967b",
        "color2": "#61b995",
        "color3": "#a3c2bc",
        "color4": "#7fa7a1",
        "color5": "#5773ab",
        "color6": "#ab373a",
        "color7": "#3e3e3e",
        "color8": "#bbbaba",
        "color9": "#a6967b",
        "color10": "#61b995",
        "color11": "#a3c2bc",
        "color12": "#7fa7a1",
        "color13": "#5773ab",
        "color14": "#ab373a",
        "color15": "#3e3e3e"
    }
}